__init__.py
dateutil_br.py
dateutil_br-0.0.7.dist-info/LICENSE
dateutil_br-0.0.7.dist-info/METADATA
dateutil_br-0.0.7.dist-info/WHEEL
dateutil_br-0.0.7.dist-info/top_level.txt
dateutil_br-0.0.7.dist-info/RECORD
